pyfcomb-2.1.2.dist-info/METADATA
pyfcomb-2.1.2.dist-info/WHEEL
pyfcomb/__init__.py
pyfcomb/reader.py
pyfcomb/rfcomb.cpython-39-darwin.so
pyfcomb-2.1.2.dist-info/RECORD
