Metadata-Version: 2.3
Name: pyfcomb
Version: 2.1.2
